{
    "success": 1,
    "data": {
        "ID": "6597",
        "NAME": "Cánh Cổng Thời Gian",
        "CHAPTER": [
            {
                "id": "2348212",
                "name": "Chương 1:Những Giấc Mơ Về Cánh Cổng Thời Gian ( Phần 1)"
            }
        ],
        "TOTALCHAPTER": "8",
        "IMG": "https://static.cdnno.com/poster//150.jpg",
        "CAT": "Xuyên Không",
        "AUTHOR": "235nguyet",
        "TRANS": "Nhiều Converter",
        "DESC": "Câu truyện kể vè một cô bé mơ đến một giấc mơ về cánh cổng thời gian từ một chú gấu xám do thiên sứ ban xuống. Cô bé đó tên là Tinh Linh và với cô bạn là Song ngư là học sinh lớp 5b.<br />\r\n  Vì trong một lần tình cờ Tinh Linh lượm được con gấu liền quay vè lớp. Tinh Linh đưa con gấu cho Song ngư như là quà tặng vì thấy chú gấu hơi dơ nên Tinh Linh nói:<br />\r\n-Cậu đem giặt rồi phơi lên nhé xin lỗi vì đây là con gấu mình nhặt nhưng nó rất dễ thương nên mình không nỡ bỏ nên mình đem lên đây tặng cậu,<br />\r\n- Cậu đúng là có một tấm lòng nhân hậu. Đến cả con gấu cậu cũng không nỡ dứt bỏ nếu là người khác thì con gấu này đã vứt, Mình hứa sẽ giữ gìn nó cẩn thận cho cậu.<br />\r\n- Tối nay mình đến ngủ nhờ nhà cậu để ôn bài mai thi toán nhé.<br />\r\n- Được thôi. Có gì đâu mà.<br />\r\nTối hôm đó, Tinh Linh sang nhà của Song Ngư. Khi về nhà Tinh Linh đã nói với bố mẹ là tối nay đến nhà Song Ngư ôn bài để mai thi toán. Bố mẹ liền gật đầu đồng ý,  vì con mình sắp thi nên mới cho Tinh Linh đi ôn bài với bạn. Khi gặp Tinh Linh song ngư liền chào:<br />\r\n-Chào Linh Tinh, mời cậu vào nhà.<br />\r\n-Chào Song Ngư, cảm ơn vì đã cho mình ngủ nhờ đêm nay.<br />\r\n- Có gì đâu chúng ta là bạn với nhau mà.<br />\r\n- Ừ.<br />\r\nRồi Song ngư dẫn Tinh Linh lên phòng. Song ngư liền chạy xuống bếp pha trà lấy bánh mời Tinh Linh ăn và chuẩn bị ôn bài cho kỳ thi ngày mai. Song ngư cầm chú gấu mà Tinh Linh tặng đã được giặt sạch và phơi khô trong phòng. Hai người bắt đầu học bài thì nghe thấy tiếng nói của ai đó. Hai người đi qua đi lại tìm kiếm ai đã nói. Và rồi thấy chú gấu đang đúng trên bàn học cất tiếng:<br />\r\n-Cảm ơn hai chị đã cứu em.<br />\r\n-Vậy em là ai? Song ngư hỏi chú gấu với khuôn mặt ngạc nhên<br />\r\n-dạ em là chú gấu ước nguyện của thiên sứ , nhưng bị đày xuống đây vì quá ham chơi ý mà.<br />\r\n-Trời ơi em ở trên đó chắc quậy banh nhà lầu luôn quá nên mới bị dày xuống đây chứ gì.<br />\r\n- Có đâu em hứa ở đây sẽ ngoan không quậy đâu nhưng cũng rất cảm ơn hai chị vì đã cứu em.<br />\r\n- Em cho chị một điều ước được không? Tinh Linh vui vẻ hỏi.<br />\r\n-Dạ được chị muốn ước gì?<br />\r\n- Chị muốn đến một nơi thật đẹp bằng cánh cổng thời gian.<br />\r\n- Được nếu chị muốn thì mỗi khi chị muốn đi thì hãy đọc \" Cánh cổng của thời gian hãy dẫn ta đến với nơi mà ta muốn đến\"  đọc xong tùy chị muốn đi đâu cũng được cả. Còn khi chị muốn quay về thì đọc: \" Cánh cổng của thời gian hãy đưa ta quay trở lại\" Thì nó sẽ cho chị quay lại thời gian lúc ban đầu mà chị xuất phát.<br />\r\n-Cảm ơn em.<br />\r\n-Này Tinh  Linh có tính làm bài không đó.<br />\r\n-Có có.<br />\r\nKể từ đó một cuộc phiêu lưu với Tinh Linh bắt đầu, Mời mọi người đón đọc chap 1 vào ngày thứ ba 12/7 nha",
        "THUMB": "https://static.cdnno.com/poster//150.jpg"
    },
    "errorCode": 0,
    "errorMessage": ""
}