{
    "success": 1,
    "data": {
        "ID": "2807",
        "NAME": "Tiên Giới Tu Tiên",
        "CHAPTER": [
            {
                "id": "933310",
                "name": "Chương 1: Tiên Giới"
            }
        ],
        "TOTALCHAPTER": "584",
        "IMG": "https://static.cdnno.com/poster//150.jpg",
        "CAT": "Tiên Hiệp",
        "AUTHOR": "Mạc Mặc",
        "TRANS": "Nhiều converter",
        "DESC": "Nói đến tác giả Mạc Mặc chắc chắn là các bạn sẽ nghĩ ngay tới Vô Thường hay Vũ Luyện Điên Phong đúng không.<br />\r\n <br />\r\nVâng, lại một tác phẩm nữa của tác giả Mặc Mặc-Tiểu thuyết xếp trong top 50 của Bạch Mã Thư Viện, kể về lịch sử phấn đấu của một “tân thủ” tại Tiên giới - Một gã phàm nhân tay ôm chặt lấy cặp đùi trắng muốt của tiên nữ, cùng nhau phi thăng lên Tiên giới. Tại Tiên giới hắn không ngừng gặp những biến cố kỳ lạ, phát triển lực lượng của bản thân khiến cho các thế lực lớn của Tiên giới phải lác mắt ngước nhìn, sợ hãi bất an. Hắn có một sủng vật là một tiên thú cường đại, trơ trẽn vô song (cũng như con người của hắn).<br />\r\n <br />\r\nMột phàm nhân chân ướt chân ráo tiến vào một thế giới mới với đủ mọi âm mưu quỷ kế. Nếu có khó khăn, hắn chỉ làm một việc duy nhất để đối phó. Ở đây NVC sẽ không như Dương Khai bên Vũ Luyện Điên Phong và cũng không giống như Đường Phong bên Vô Thường. NVC sẽ pha 1 chút vô sỉ, 1 chút háo sắc.........<br />\r\n <br />\r\nHãy cùng đọc và cảm nhận!____________",
        "THUMB": "https://static.cdnno.com/poster//150.jpg"
    },
    "errorCode": 0,
    "errorMessage": ""
}