{
    "success": 1,
    "data": {
        "ID": "2492",
        "NAME": "Vạn Giới Hệ Thống Edit",
        "CHAPTER": [
            {
                "id": "820949",
                "name": "Chương 1: Hận Thiên bất công, hận mình vô năng!"
            }
        ],
        "TOTALCHAPTER": "3",
        "IMG": "https://static.cdnno.com/poster//150.jpg",
        "CAT": "Huyền Ảo",
        "AUTHOR": "Di Sát",
        "TRANS": "۩£oli»Sâu±Đế",
        "DESC": "vạn giới hệ thống xuy&ecirc;n qua ức vạn đại thi&ecirc;n thế giới , đi theo nh&acirc;n vật ch&iacute;nh ch&acirc;n của bước , c&ugrave;ng nhau trải qua một đoạn lại một đoạn đặc sắc đ&iacute;ch lữ tr&igrave;nh .\r\n<br /> khi l&acirc;m ti&ecirc;u đạp chư thần quần ma đ&iacute;ch thi thể , đi l&ecirc;n kia ch&iacute; cao đ&iacute;ch vương tọa , hắn đem n&oacute;i cho thế nh&acirc;n , con kiến h&ocirc;i cũng nhưng lay trời .\r\n<br /> lấy địa cầu v&igrave; khởi điểm , mi&ecirc;u hội một bức tr&agrave;n đầy huyền huyễn sắc th&aacute;i đ&iacute;ch vũ trụ bức họa , ở chỗ n&agrave;y , ngươi đem thấy địa cầu ra đ&iacute;ch thần kỳ thế giới , ở chỗ n&agrave;y , ngươi đem thấy được một ho&agrave;n to&agrave;n kh&aacute;c nhau đ&iacute;ch thế giới .\r\n<br /> chủ yếu trải qua thế giới ：GTA5、 hắc lợi ba đặc 、 mới tiếu ngạo giang hồ 、 Lục Tiểu Phượng truyền kỳ 、 mục ph&aacute;p đại lục 、 phong v&acirc;n 、 b&aacute;o th&ugrave; người li&ecirc;n minh 、 tru ti&ecirc;n thế giới （ tr&ograve; chơi bản ）......",
        "THUMB": "https://static.cdnno.com/poster//150.jpg"
    },
    "errorCode": 0,
    "errorMessage": ""
}