{
    "success": 1,
    "data": {
        "ID": "3760",
        "NAME": "Không Tưởng Hạm Nương",
        "CHAPTER": [],
        "TOTALCHAPTER": "0",
        "IMG": "https://static.cdnno.com/poster//150.jpg",
        "CAT": "Khoa Huyễn",
        "AUTHOR": "Âu Châu Đề Đốc",
        "TRANS": "Kaisermtv",
        "DESC": "Đối với kh&ocirc;ng tưởng hạm đội tới n&oacute;i, kẻ địch lớn nhất cũng kh&ocirc;ng phải tới tự tr&ecirc;n mặt biển qu&aacute;i vật, m&agrave; l&agrave; ở c&aacute;c n&agrave;ng trong tổ chức c&aacute;i kia nhất l&agrave; cao cao tại thượng Đề đốc đại nh&acirc;n.<br /><br />\"Nhanh ngăn cản Đề đốc! Hắn lại phải lớn hơn kiến rồi!\"<br /><br />\"Tại sao kh&ocirc;ng thừa nhận ch&iacute;nh m&igrave;nh l&agrave; một c&aacute;i người Phi ch&acirc;u!\"<br /><br />\"C&aacute;c ngươi c&acirc;m miệng cho ta! Ta nhất định sẽ đ&aacute;nh cược đi ra đại c&ugrave;ng!\"<br /><br />Hai mắt đỏ ch&oacute;t Đề đốc quay về ph&iacute;a sau số 111 kế hoạch hạm Hạm Nương giận dữ h&eacute;t.<br /><br />(quyển s&aacute;ch thế giới quan v&igrave; l&agrave; gần tương lai, cũng kh&ocirc;ng phải l&agrave; game, nếu như nh&igrave;n thấy thế giới quan xung đột, lấy quyển s&aacute;ch thế giới quan l&agrave;m chủ. Cảm tạ hợp t&aacute;c ~)",
        "THUMB": "https://static.cdnno.com/poster//150.jpg"
    },
    "errorCode": 0,
    "errorMessage": ""
}