{
    "success": 1,
    "data": {
        "ID": "11105",
        "NAME": "Biến Thân Chi Loạn Thế Giai Nhân",
        "CHAPTER": [
            {
                "id": "3666760",
                "name": "Chương 1: Quan Trung"
            }
        ],
        "TOTALCHAPTER": "10",
        "IMG": "https://static.cdnno.com/poster//150.jpg",
        "CAT": "Kiếm Hiệp, Lịch Sử, Đồng Nhân",
        "AUTHOR": "Ngọc Diệu Tiêu Mạnh Thường",
        "TRANS": "CrossFireZero",
        "DESC": "Biến thân chi loạn thế giai nhân tóm tắt: Xuyên qua tam quốc, chư hầu nổi lên, Đổng Trác nhận lệnh nhập kinh, thiên hạ sắp đại loạn, biến thân trở thành tuyệt sắc nữ tử Thi Tịch lại nên đi nơi nào...<br />\r\nTặc đồ tác loạn, quỷ quái hoành hành, Thần Châu đại địa trăm họ lầm than, bá tánh trôi giạt khắp nơi, xác chết đói khắp nơi.<br />\r\nTrong lúc này, quần hùng tranh giành, cực kì hiếu chiến, họa loạn thiên hạ.<br />\r\nNgoài ý muốn kế thừa yêu hoàng huyết mạch thư làm, có không bằng vào trong ngực cẩm tú, kham bình thiên hạ, chung kết loạn thế.<br />\r\nVô tận loạn thế, gió lửa giai nhân, bởi vậy bắt đầu...<br />\r\nps: Bổn chuyện xưa chỉ do hư cấu, như có tương đồng, chỉ do trùng hợp.",
        "THUMB": "https://static.cdnno.com/poster//150.jpg"
    },
    "errorCode": 0,
    "errorMessage": ""
}