{
    "success": 1,
    "data": {
        "ID": "5706",
        "NAME": "Dị thế long xà",
        "CHAPTER": [
            {
                "id": "2053198",
                "name": "Chương 1: Chuyển sinh tiểu thuyết: Dị thế long xà tác giả: Kiếm ách hư không"
            }
        ],
        "TOTALCHAPTER": "215",
        "IMG": "https://static.cdnno.com/poster//150.jpg",
        "CAT": "Tiên Hiệp, Xuyên Không",
        "AUTHOR": "Kiếm ách hư không",
        "TRANS": "dinhnhan",
        "DESC": "Đại Thành vương triều, trải qua tây đông hai phần mười, cho đến đông thành truyền cho mười chín thế thời, thiên hạ trải qua hai trăm năm diễn kịch, nguyên tây thành phong sáu mươi bốn đại quốc, 125 tiểu quốc, to nhỏ hiếm hoi còn sót lại hai mươi lại ba.<br />\r\n<br />\r\n\tLúc đó, có thái, trần, ung, kinh, theo ngũ đại Chiến quốc cũng mạnh hơn thế, đều sẵn sàng ra trận lấy dòm ngó thành thất, có bao gồm hết vũ nội, bao quát tứ hải, thôn tính bát hoang chi tâm.<br />\r\n<br />\r\n\tThiên hạ phân tranh, binh qua nổi lên bốn phía, tiến vào Chiến quốc thời loạn lạc.<br />\r\n<br />\r\n\tThời năm, đúng lúc gặp thiên địa sát kiếp, hư không sụp đổ, quy tắc đại loạn, cứ thế Thiên Thần không được an tọa, đều bị thứ tự quét xuống phàm trần.<br />\r\n<br />\r\n\tTrong lúc nhất thời, Thiên Thần mưu cầu quay về, địa chi dòm ngó với ngày, bách gia chư muốn mượn cơ hội từng người thành Đạo, người quỷ, Yêu Ma cũng không chịu cô đơn, toàn bộ thế giới Thần Ma múa tung, rơi vào ở khắp mọi nơi hỗn loạn cùng giết chóc bên trong.<br />\r\n<br />\r\n\tĐang lúc đó, Vương Việt, một vị đến từ Địa cầu hiện đại mạt pháp chi niên người tu hành, nhờ cơ duyên, chuyển sinh này vực.",
        "THUMB": "https://static.cdnno.com/poster//150.jpg"
    },
    "errorCode": 0,
    "errorMessage": ""
}