{
    "success": 1,
    "data": {
        "ID": "3541",
        "NAME": "Vũ Tôn",
        "CHAPTER": [
            {
                "id": "1225172",
                "name": "Chương 1 : Linh Tôn"
            }
        ],
        "TOTALCHAPTER": "254",
        "IMG": "https://static.cdnno.com/poster//150.jpg",
        "CAT": "Huyền Ảo, Trùng Sinh",
        "AUTHOR": "TrungCTH",
        "TRANS": "Nhiều Converter",
        "DESC": "Nếu thấy truyện hay, tác giả sẽ rất vui khi mọi người đề cử bằng nguyệt phiếu hoặc vote 10 sao. Đó là động lực để mình tiếp tục cố gắng viết tiếp :)<br />\r\n<br />\r\nVũ Trụ một trong tứ đại chúa tể, Linh Tôn cùng Tam ca Minh Tôn vì phát hiện ra 1 bí mật  của Đại ca và Nhị ca của họ mà bị truy sát.  <br />\r\n<br />\r\nMinh Tôn liều chết tạo 1 cơ hội cho Linh Tôn chuyển thế tu luyện nhằm bước ra 1 bước cuối để có thể sánh vai chống lại Đại ca cùng Nhị ca.  <br />\r\n<br />\r\n1 Tuyệt Thế Vũ Tôn sau khi chuyển thế sẽ thế nào ? Thiên Vũ sẽ bị hắn quậy nát ra sao ? Thiên tài, yêu nghiệt thì sao ? Tất cả đều bị Linh Tôn ta đạp dưới gót chân. Thiên Vũ này sẽ trường tồn vĩnh cửu khi nào ta còn tồn tại. <br />\r\n<br />\r\n \" Kẻ nào khinh thường ta, ta trả lại gấp trăm. Kẻ nào nhục nhã ta, ta trả hắn gấp vạn. \" - Vũ Tôn .<br />\r\n<br />\r\nTruyện VN sáng tác 100% nhé, mong mọi người ủng hộ, góp ý nhiều.",
        "THUMB": "https://static.cdnno.com/poster//150.jpg"
    },
    "errorCode": 0,
    "errorMessage": ""
}