{
    "success": 1,
    "data": {
        "ID": "2700",
        "NAME": "Võng Du Chi Sủng Vật Tiểu Tinh Linh",
        "CHAPTER": [
            {
                "id": "887759",
                "name": "Chương 1: Ngã xuống vương giả - Quyển 1"
            }
        ],
        "TOTALCHAPTER": "287",
        "IMG": "https://static.cdnno.com/poster//150.jpg",
        "CAT": "Võng Du",
        "AUTHOR": "Thiên Tứ Tam Lang",
        "TRANS": "Hoàng Luân",
        "DESC": "Một t&ecirc;n Otaku nam chi t&acirc;m, cũng có th&ecirc;̉ k&eacute;o nổi thế giới biến đổi lớn.<br /><br />Xem vai ch&iacute;nh như thế n&agrave;o theo một g&atilde; người kh&ocirc;ng c&oacute; đồng n&agrave;o tiểu tử ngh&egrave;o, từng bước một phát tri&ecirc;̉n l&agrave; pokemon li&ecirc;n minh Hắc &Aacute;m Thế Giới duy nhất vương.<br /><br />&Ocirc;ng Vua kh&ocirc;ng ngai!",
        "THUMB": "https://static.cdnno.com/poster//150.jpg"
    },
    "errorCode": 0,
    "errorMessage": ""
}