{
    "success": 1,
    "data": {
        "ID": "11697",
        "NAME": "Khoa Kỹ Vấn Đạo",
        "CHAPTER": [
            {
                "id": "3853668",
                "name": "Chương 1: Gặp Nạn"
            }
        ],
        "TOTALCHAPTER": "91",
        "IMG": "https://static.cdnno.com/poster//150.jpg",
        "CAT": "Đô Thị, Trùng Sinh",
        "AUTHOR": "HoaTrungLu",
        "TRANS": "Nhiều Converter",
        "DESC": "Đây là một câu chuyện lấy bối cảnh đất nước thời kỳ đầu đổi mới, nhân vật chính bị rơi máy bay trên Đại Tây Dương, trọng sinh về năm 2001 cùng với những bí mật của một nền văn minh cổ đã biến mất, Atlantis. Main đã lợi dụng những tri thức có được từ nền văn minh này để xây dựng lên đế chế công nghệ, thực hiện lý tưởng của mình, vươn tới nhân sinh đỉnh cao. Câu chuyện là cả một quá trình nhân vật chính đấu tranh hoàn thành mộng tưởng nhân sinh, có âm mưu, ân oán, có tình yêu và nước mắt... Hãy cùng xem main trưởng thành như thế nào, thế giới quan biến đổi ra sao khi nắm trong tay những công nghệ siêu việt thời đại kế thừa từ nền văn mình trước, để từ đó thay đổi đời sống nhân loại theo một cách hoàn toàn khác bây giờ. Xin mời các bạn đọc truyện!",
        "THUMB": "https://static.cdnno.com/poster//150.jpg"
    },
    "errorCode": 0,
    "errorMessage": ""
}