{
    "success": 1,
    "data": {
        "ID": "3921",
        "NAME": "Tiếu Ngạo Hoa Hạ",
        "CHAPTER": [
            {
                "id": "1402813",
                "name": "Chương 1: Nhớ lại"
            }
        ],
        "TOTALCHAPTER": "1056",
        "IMG": "https://static.cdnno.com/poster//150.jpg",
        "CAT": "Đô Thị",
        "AUTHOR": "Tiếu Dạ Lãnh Phong",
        "TRANS": "trang4mat",
        "DESC": "Diệp Ph&agrave;m, một đứa c&ocirc; nhi, bởi v&igrave; thi&ecirc;n tư th&ocirc;ng minh, hai tuổi năm đ&oacute; bị một c&aacute;i l&aacute;nh đời cao nh&acirc;n thu dưỡng, học y luyện v&otilde;, cầm kỳ thư họa, kh&ocirc;ng chỗ n&agrave;o kh&ocirc;ng th&ocirc;ng. Mười s&aacute;u tuổi năm đ&oacute;, sư ph&oacute; bởi v&igrave; kh&ocirc;ng l&acirc;u tại nh&acirc;n thế, cưỡng &eacute;p bức b&aacute;ch Diệp Ph&agrave;m xuống n&uacute;i lưu lạc.<br /><br />Xuống n&uacute;i sau đ&iacute;ch Diệp Ph&agrave;m phi&ecirc;u dương qua biển, đi v&agrave;o xa x&ocirc;i Anh quốc, lợi dụng t&aacute;m năm thời gian, một tay s&aacute;ng lập thuộc về m&igrave;nh bu&ocirc;n b&aacute;n Thần Thoại Vi&ecirc;m Ho&agrave;ng tập đo&agrave;n, c&ocirc;ng th&agrave;nh danh toại về sau, Diệp Ph&agrave;m c&oacute; chút thể x&aacute;c v&agrave; tinh thần đều mệt, dứt kho&aacute;t về nước chuẩn bị qua một đoạn b&igrave;nh thường sinh hoạt, sau khi về nước, Diệp Ph&agrave;m thật c&oacute; thể như nguyện sao? Đối mặt kh&ocirc;ng ngừng diễm ngộ, quyền lợi hấp dẫn, thế tục th&agrave;nh kiến, Diệp Ph&agrave;m n&ecirc;n như thế n&agrave;o đối mặt? L&agrave; lựa chọn b&igrave;nh thường sinh hoạt hay vẫn l&agrave; Ngạo Khiếu đ&ocirc; thị? L&agrave; ẩn cư n&uacute;i rừng hay vẫn l&agrave; leo l&ecirc;n đỉnh phong? Hết thảy tất cả đều c&ugrave;ng đợi Diệp Ph&agrave;m đi lựa chọn. Hỏi bao la mờ mịt đại địa, ai chủ ch&igrave;m nổi, Diệp Ph&agrave;m tai!",
        "THUMB": "https://static.cdnno.com/poster//150.jpg"
    },
    "errorCode": 0,
    "errorMessage": ""
}