{
    "success": 1,
    "data": {
        "ID": "8922",
        "NAME": "Trở Lại Lúc Xưa",
        "CHAPTER": [
            {
                "id": "3036536",
                "name": "Chương 1: : Trở lại 1994"
            }
        ],
        "TOTALCHAPTER": "340",
        "IMG": "https://static.cdnno.com/poster//150.jpg",
        "CAT": "Đô Thị, Dị Năng",
        "AUTHOR": "Ngã cật băng trấn chanh tử",
        "TRANS": "๖ۣۜTiếu ๖ۣۜHồng ๖ۣۜTrần",
        "DESC": "Chán nản thanh niên Lâm Dương , trở lại tuổi thơ , làm cái gì chắc cái đó , đi lên Quang Minh Đại Đạo.<br />\r\n<br />\r\nchuyện kén người đọc, không có yy, không có lợi dụng biết trước kinh doanh ( còn quá nhỏ ) main đam mê theo viết tiểu thuyết, chủ yếu nói về những phấn đấu lúc nhỏ về học tập, cũng như bắt đầu... mối tình đầu @@!",
        "THUMB": "https://static.cdnno.com/poster//150.jpg"
    },
    "errorCode": 0,
    "errorMessage": ""
}