{
    "success": 1,
    "data": {
        "ID": "6566",
        "NAME": "Vong Linh Viễn Chinh",
        "CHAPTER": [
            {
                "id": "2338318",
                "name": "Chương 1: Xuyên qua vong linh giới"
            }
        ],
        "TOTALCHAPTER": "399",
        "IMG": "https://static.cdnno.com/poster//150.jpg",
        "CAT": "Võng Du, Dị Giới, Khoa Huyễn, Xuyên Không",
        "AUTHOR": "Hôi lãnh người",
        "TRANS": "http://dichtienghoa.com/",
        "DESC": "Mang theo hệ thống xuyên qua 1 vũ trụ khác.Ban đầu đượcj hệ thống cho cái căn cứ tộc undead trong warcarft 3,về sau  thì dùng 1 số map trong warcarft 3 làm phó bản kiếm đồ.<br />\r\n<br />\r\n<br />\r\nTruyện được cái viết về cái hệ thống cùng cách pt của nvc khá hợp lí,nvc bit cach che dấu pt dần từ từ,mạnh nhưng ko ngáo đá",
        "THUMB": "https://static.cdnno.com/poster//150.jpg"
    },
    "errorCode": 0,
    "errorMessage": ""
}