{
    "success": 1,
    "data": {
        "ID": "5621",
        "NAME": "Ngự Long Kiếm Tiên",
        "CHAPTER": [
            {
                "id": "1997187",
                "name": "Chương 1: Vây chương"
            }
        ],
        "TOTALCHAPTER": "802",
        "IMG": "https://static.cdnno.com/poster//150.jpg",
        "CAT": "Tiên Hiệp",
        "AUTHOR": "Lão Hoàng",
        "TRANS": "Tiêu Dao",
        "DESC": "\"Tung ho&agrave;nh Ti&ecirc;n giới, ngự kiếm Thừa Long, ta chi nguyện đấy! Chẳng qua l&agrave; \" \"Kia Long tại sao chợt nh&igrave;n giống như con giun? !<br /> Thật nhiều tại sao l&agrave; của ta mỗi một buổi tối bị bao đi ra ngo&agrave;i? ! \" <br /> Một c&aacute;i đả thương Long, một quyển kh&aacute;c hẳn với b&igrave;nh thường bản bổn  &laquo; Phong L&acirc;m Hỏa Sơn b&iacute; quyết &raquo; ,<br /> Đ&ocirc; Thi&ecirc;n Ti&ecirc;n giới b&igrave;nh thường thiếu ni&ecirc;n Triệu Vũ nhiệt huyết tu h&agrave;nh đường l&uacute;c đ&oacute; bắt đầu! <br /> p/s: cầu thank vote tốt ^^<br /> truyện của Ti&ecirc;u Dao : http://truyencv.com/truyen-dang-boi/24453/",
        "THUMB": "https://static.cdnno.com/poster//150.jpg"
    },
    "errorCode": 0,
    "errorMessage": ""
}