{
    "success": 1,
    "data": {
        "ID": "8687",
        "NAME": "Chân Vũ Đãng Ma Truyện",
        "CHAPTER": [
            {
                "id": "2972160",
                "name": "..."
            }
        ],
        "TOTALCHAPTER": "3",
        "IMG": "https://static.cdnno.com/poster//150.jpg",
        "CAT": "Tiên Hiệp",
        "AUTHOR": "vxcv",
        "TRANS": "...m",
        "DESC": "...",
        "THUMB": "https://static.cdnno.com/poster//150.jpg"
    },
    "errorCode": 0,
    "errorMessage": ""
}