{
    "success": 1,
    "data": {
        "ID": "3922",
        "NAME": "Thiên Phủ Truyền Thuyết",
        "CHAPTER": [
            {
                "id": "1403887",
                "name": "Chương 1: Nửa chỉ trên núi"
            }
        ],
        "TOTALCHAPTER": "1006",
        "IMG": "https://static.cdnno.com/poster//150.jpg",
        "CAT": "Huyền Ảo",
        "AUTHOR": "Tòng Lai Bất Tri Tử",
        "TRANS": "traitim_phale",
        "DESC": "Vạn dặm giang sơn như vẽ b&igrave;nh, Ti&ecirc;n Ma y&ecirc;u nh&acirc;n đại đại sinh, nho nhỏ thiếu ni&ecirc;n như thế n&agrave;o gi&atilde;y giụa vận mệnh g&ocirc;ng xiềng, đi đến trường sinh bất tử chi lộ?<br /><br />Th&acirc;n nhập nh&agrave; t&ugrave;, tao ngộ Nguy&ecirc;n Thần cao thủ bắt hiến tế, như thế n&agrave;o đ&agrave;o tho&aacute;t c&aacute;i n&agrave;y c&aacute;i thế hung ma chi thủ?<br /><br />Vị h&ocirc;n th&ecirc; thần hồn t&agrave;n ph&aacute;, ch&iacute;nh m&igrave;nh lại th&uacute;c thủ v&ocirc; s&aacute;ch, l&agrave;m sao c&oacute; thể cứu v&atilde;n trong l&ograve;ng t&igrave;nh cảm ch&acirc;n th&agrave;nh?<br /><br />Thi&ecirc;n Đạo bất c&ocirc;ng, vận mệnh l&agrave;m nhiều điều sai tr&aacute;i, nhưng ta tin tưởng ta ch&iacute;nh l&agrave; thi&ecirc;n mệnh chi nh&acirc;n, mặc ngươi vạn",
        "THUMB": "https://static.cdnno.com/poster//150.jpg"
    },
    "errorCode": 0,
    "errorMessage": ""
}