{
    "success": 1,
    "data": {
        "ID": "7303",
        "NAME": "Ma Vật Nương Sổ Tay",
        "CHAPTER": [
            {
                "id": "2595540",
                "name": "Chương 1: Nam nhân ở ngực có thất tinh Minh Văn!"
            }
        ],
        "TOTALCHAPTER": "435",
        "IMG": "https://static.cdnno.com/poster//150.jpg",
        "CAT": "Xuyên Không",
        "AUTHOR": "Tinh Hùng Dũng Nghi",
        "TRANS": "♚๖ۣۜKabigon♌♔",
        "DESC": "L&atilde;o tử thuộc t&iacute;nh rốt cục ph&aacute; trăm vạn! Ta đ&atilde; thi&ecirc;n hạ v&ocirc; địch! ! ! !<br /> <br /> A ha! A ha! A ha ha ha! !<br /> <br /> Đinh! Hệ thống ph&aacute;t hiện ma vật nương, kiểm trắc b&ecirc;n trong...<br /> <br /> Ma vật nương đơn thuộc t&iacute;nh ph&aacute; ức...<br /> <br /> Si&ecirc;u cấp nguy hiểm.<br /> <br /> P/s: truyện bẩn bựa c&oacute; thể kh&ocirc;ng hợp với một số bạn xin đừng troll vote",
        "THUMB": "https://static.cdnno.com/poster//150.jpg"
    },
    "errorCode": 0,
    "errorMessage": ""
}