{
    "success": 1,
    "data": {
        "ID": "7161",
        "NAME": "Đạo Ma Hiệp Khách",
        "CHAPTER": [
            {
                "id": "2554918",
                "name": "Chương 1:  Thế giới mới"
            }
        ],
        "TOTALCHAPTER": "2",
        "IMG": "https://static.cdnno.com/poster//150.jpg",
        "CAT": "Tiên Hiệp, Kiếm Hiệp, Võng Du, Trùng Sinh",
        "AUTHOR": "Atlas",
        "TRANS": "Nhiều Converter",
        "DESC": "Tác phẩm đầu tay của tui, mong các xemer của truyện góp ý, nhận xét( hay hoặc dở, nhàm chán cứ nói để tg biết đường sửa đổi giúp truyện có hướng đi tích cực hơn).chân thành cảm ơn. :))<br />\r\nTruyện kể về 1 thằng main tên là Đuờng Khánh nhị thiếu gia của gia tộc họ Đường  có tập đoàn sản xuất trò chơi điện tử nổi tiếng khắp châu lục. Là nhị thiếu nhưng thực chất là con nuôi dc gia chủ Đuờng Khắc và phu nhân Mi Nhã đem về từ trại mồ côi khi mà đến thăm nơi này do đang làm từ thiện( biết v thôi nhé, tuổi thơ khỏ kể, luời vl).<br />\r\n  Lên 18t main là người làm khuynh đảo thế giới, vang danh khắp cả TĐ khi là nguời đầu tiên lập trình hệ thống game thực tế- ảo đầu tiên trên thế giới mang tên Hiệp khách hệ thống tương tác qua chiếc nhẫn do hắn thiết kế. <br />\r\nHắn có tất cả mọi thứ trên đời khi tuổi chưa quá 20 và cũng chỉ đến đây mà thôi. <br />\r\nVào ngày 30/3/2095 chính sinh nhật cua hắn tập đoàn đã xảy ra cuộc đảo chính, đại thiếu gia Đường Nghĩa lo sợ sẽ mất đi quyềm thừa kế  tập đoàn vào tay ng em vốn dĩ ko nên có trên đời này nên đã bí mật ám sát, hạ độc tiễn em trai hắn qua thế giới bên kia.( thế giới nào thì chưa biết :v)<br />\r\nHắn trọng sinh vào 1 thế giới hoàn toàn khác tđ, nơi có những cuờng thế võ giả, tu luyện, một nơi có thực lực mời có đất sống. <br />\r\nVới hệ thống trong tay, liệu hắn c thể trở nên cường đại dc hay ko?? Nào là tiền bac danh vọng, mỹ nữ( yên tâm là có dàn harem nhé với độ yy vừa phải ) sẽ ko làm mn thất vọng đâu =))) kính momg mn đón xem. <br />\r\nCầu thank, cầu vote!!!!!",
        "THUMB": "https://static.cdnno.com/poster//150.jpg"
    },
    "errorCode": 0,
    "errorMessage": ""
}