{
    "success": 1,
    "data": {
        "ID": "6797",
        "NAME": "Võng Du Chi Hỗn Nguyên Pháp Sư",
        "CHAPTER": [
            {
                "id": "2422529",
                "name": "Chương 1: Thương Khung"
            }
        ],
        "TOTALCHAPTER": "450",
        "IMG": "https://static.cdnno.com/poster//150.jpg",
        "CAT": "Võng Du",
        "AUTHOR": "Tục Tả Thanh Xuân - 续写青春",
        "TRANS": "AyaHayate",
        "DESC": "Hỏa hệ ma pháp cuồng dã thô bạo, Lôi hệ ma pháp thần bí huyễn khốc, Thủy hệ ma pháp công phòng một thể, Thổ hệ ma pháp trầm ổn dày nặng...<br />\r\n<br />\r\n\tCác hệ ma pháp đều có bản thân độc nhất vô nhị chỗ thích hợp, khi một người có thể sử dụng hết thảy ma pháp, cũng đưa chúng nó thông hiểu đạo lí thời điểm, người này đều sẽ là không thể chống đối!<br />\r\n<br />\r\n\tLâm Hiên: Người khác thành thần cần vạn ngàn phản phái tiền phó hậu kế!<br />\r\n<br />\r\n\tMà ta chỉ trong một ý nghĩ!<br />\r\n<br />\r\n\tTác giả: Đừng lớn lối như vậy! Ngươi xem ngươi đều đem thư hữu cho doạ chạy!<br />\r\n<br />\r\n---------------------<br />\r\ntruyện ra 360c rồi nhé @_@",
        "THUMB": "https://static.cdnno.com/poster//150.jpg"
    },
    "errorCode": 0,
    "errorMessage": ""
}