{
    "success": 1,
    "data": {
        "ID": "7809",
        "NAME": "Cửu Kiếm Quy Nhất",
        "CHAPTER": [
            {
                "id": "2756778",
                "name": "Chương 1: : Đêm Kinh Phong"
            }
        ],
        "TOTALCHAPTER": "15",
        "IMG": "https://static.cdnno.com/poster//150.jpg",
        "CAT": "Huyền Ảo, Dị Giới",
        "AUTHOR": "Hào Đĩnh Đế Quân",
        "TRANS": "Harley Quinn",
        "DESC": "Hắn, gọi Trần Hiên Lục hắn, là Thủy Kính truyền nhân, Lưu Hầu Cơ lương đệ tử hắn, đạt được Hạng Vũ tự mình thụ dư Bá Vương Chiến Thần Thương lại suốt đời độc ái sử chiêu đó tuyệt tích thiên hạ Độc Cô Cửu Kiếm hắn, sinh ra ở Đông Hán những năm cuối, nhưng hiểu nhau tương giao tương nhu dĩ mạt cũng năm 2000 sau tình cảm chân thành hắn, phong mang, Cửu Châu cộng hưởng nàng, đao phong, quỷ thần cùng buồn nhìn hắn như thế nào xuyên qua ở các thời không ranh giới, sáng tạo hạ truyền kỳ đại chiến Kim Cổ tình, tuyệt tích Đại Vũ Song Kiếm thỉnh thoảng cũng sẽ cùng ô mai trường Tô uống chén trà xanh quyến luyến Phong Trần gian, Cửu Kiếm đã quy nhất trẫm giang sơn tùy ngươi cầm, trẫm Vương Đình mặc cho ngươi lấy trẫm chỉ nguyện cùng ta Mộc Tử Vũ tiêu sái nhân gian, hỏi thăm Thương Khung...",
        "THUMB": "https://static.cdnno.com/poster//150.jpg"
    },
    "errorCode": 0,
    "errorMessage": ""
}