{
    "success": 1,
    "data": {
        "ID": "9630",
        "NAME": "Dâm Ma Tông Chủ",
        "CHAPTER": [
            {
                "id": "3252550",
                "name": "Chương 1: Trần Tiêu (edit)"
            }
        ],
        "TOTALCHAPTER": "8",
        "IMG": "https://static.cdnno.com/poster//150.jpg",
        "CAT": "Tiên Hiệp, Huyền Ảo, Dị Giới",
        "AUTHOR": "phudo9102000@",
        "TRANS": "Nhiều Converter",
        "DESC": "Trần Tiêu là phế vật của Trần gia. Điều này khắp cả Thanh Thạch thành không ai không biết, không ai không rõ. Có thể nói, hắn đã trở thành một người nổi tiếng nhất nhì ở toà thành thị náo nhiệt này. Ngay cả cái danh hào Thiên Hạ Đệ Nhất Phế Vật cũng được vinh dự trao tặng cho hắn. Thế nhưng, chẳng hiểu vì sao, kẻ tai tiếng như vậy lại vẫn luôn được một hoàng hoa khuê nữ đem lòng ái mộ...<br />\r\n<br />\r\nP/s: Truyện kể về quá trình chấn hưng Dâm Ma tông của Trần Tiêu. Trong quá trình đó, nhiệm vụ của hắn là thu được thật nhiều mỹ nữ và cùng họ  song tu để nâng cao thực lực.  <br />\r\n<br />\r\nTruyện khá là yy nhưng chắc chắn sẽ không thiếu logic. <br />\r\n<br />\r\nVăn phong đảm bảo không gây ức chế.<br />\r\n<br />\r\nThế giới bên trong truyện dần dần được hé lộ và rất mới lạ.",
        "THUMB": "https://static.cdnno.com/poster//150.jpg"
    },
    "errorCode": 0,
    "errorMessage": ""
}