{
    "success": 1,
    "data": {
        "ID": "5441",
        "NAME": "Loạn Thanh",
        "CHAPTER": [
            {
                "id": "1940848",
                "name": "Chương 1: Khổ rồi xuyên qua"
            }
        ],
        "TOTALCHAPTER": "115",
        "IMG": "https://static.cdnno.com/poster//150.jpg",
        "CAT": "Lịch Sử",
        "AUTHOR": "Thanh Ngọc Sư Tử",
        "TRANS": "Nhiều Converter",
        "DESC": "Năm đ&oacute;, &Yacute; qu&yacute; phi phong hoa tuyệt đại, t&uacute;c ph&ograve;ng ch&iacute;nh quyền thế ch&oacute;i chang, Hồng T&uacute; To&agrave;n b&igrave;nh y&ecirc;n đả tọa, Vi&ecirc;n Minh Vi&ecirc;n x&iacute;ch diễm che trời.<br /><br />Năm đ&oacute;, Hồ L&acirc;m Dực dốc hết t&acirc;m huyết, từng quốc phi&ecirc;n b&aacute;ch chiến gian nan, tả T&ocirc;ng Đường anh h&ugrave;ng dối gạt người, L&yacute; Hồng Chương c&aacute;nh chim dần m&atilde;n.<br /><br />Năm đ&oacute;, một t&ecirc;n tiểu viện bảo t&agrave;ng ki&ecirc;m chức người hướng dẫn, trải qua trong lịch sử tối khổ rồi xuy&ecirc;n qua, tử m&agrave; hậu sinh, tuyệt địa cầu sinh, thề muốn bằng sức một người, họa loạn cung đ&igrave;nh, lật đổ vương triều, khai s&aacute;ng một c&aacute;i ho&agrave;n to&agrave;n mới đời đời &mdash;&mdash;<br /><br />Ta kim muốn đem b&uacute;t lớn, tr&ugrave;ng tả xu&acirc;n thu, thi&ecirc;n hạ c&ograve;n như vậy, huống một nh&agrave; một thất c&ugrave;ng mấy c&aacute;i chị d&acirc;u tử?",
        "THUMB": "https://static.cdnno.com/poster//150.jpg"
    },
    "errorCode": 0,
    "errorMessage": ""
}