{
    "success": 1,
    "data": {
        "ID": "12937",
        "NAME": "Âm Dương Sinh Tử Ký",
        "CHAPTER": [
            {
                "id": "4183558",
                "name": "Chương 1: Tần Thiên Quân"
            }
        ],
        "TOTALCHAPTER": "1",
        "IMG": "https://static.cdnno.com/poster//150.jpg",
        "CAT": "Tiên Hiệp, Huyền Ảo, Dị Giới",
        "AUTHOR": "Gakuen",
        "TRANS": "Nhiều Converter",
        "DESC": "Nhất Bút Tây Lai — Sinh Tử Âm Dương...<br />\r\n<br />\r\nTu tiên giới, nhất niệm sinh, nhất niệm tử. <br />\r\n<br />\r\nTa không phải là ma, chắc chắn càng không phải là phật.<br />\r\n<br />\r\nGia hỉ nhất bộ bước ra thiên hạ sinh. Gia nộ bước ra bát hoang diệt. <br />\r\n<br />\r\nCả đời ta tu tiên không cầu trường sinh, không cầu vô địch. Ta tu tiên chính là cầu cái kia Vô Niệm. <br />\r\n<br />\r\nNhư thế nào Vô Niệm ? Thiên Địa Vạn Vật, Vạn Cổ Muôn Đời kia không còn ta không làm được. Cái kia Sinh cái kia Tử đều là tại tâm ta nhất niệm. Đợi đến lúc ta không còn gì để truy cầu, đó chính là — Vô Niệm<br />\r\n<br />\r\nĐây là một cái cố sự kể về nhân vật chính bước lên con đường tu tiên mang theo cái kia vô chính vô tà tính cách, tuỳ tâm sở dục. Lúc thì tâm như chỉ thuỷ, giếng cổ tĩnh mịch, lúc thì bá ngạo vô song, tà phô cửu thiên.<br />\r\n<br />\r\nVạn Phật cùng hiện ? Vạn Ác cùng hiển ? Quản mẹ nó chính tà. Lão tử mất hứng chính là đồ thượng Cửu Thiên, sát hạ Bích Lạc Hoàng Tuyền.<br />\r\n<br />\r\nMột tay chấp Sinh, một tay chưởng Tử. Sinh Tử đồng tu — Ngạo thị thiên hạ ! ! !",
        "THUMB": "https://static.cdnno.com/poster//150.jpg"
    },
    "errorCode": 0,
    "errorMessage": ""
}