{
    "success": 1,
    "data": {
        "ID": "8712",
        "NAME": "Mihawk : Vô Hạn Xuyên Qua",
        "CHAPTER": [
            {
                "id": "2982123",
                "name": "Chương 01 : Sự lựa chọn"
            }
        ],
        "TOTALCHAPTER": "5",
        "IMG": "https://static.cdnno.com/poster//150.jpg",
        "CAT": "Xuyên Không, Đồng Nhân",
        "AUTHOR": "tttung357@",
        "TRANS": "Nhiều Converter",
        "DESC": "1 thiếu niên được THẦN cho sống lại.<br />\r\nhắn đã chọn Dracule Mihawk !<br />\r\ntừ đây , câu truyện bắt đầu !<br />\r\n< hình như ta xóa nhầm ><br />\r\n1/1 bắt đầu viết truyện , do truyện đầu tiên ta viết nên sẽ còn sai sót nhiều , mong ae góp ý kiến cho . CẢM ƠN",
        "THUMB": "https://static.cdnno.com/poster//150.jpg"
    },
    "errorCode": 0,
    "errorMessage": ""
}