{
    "success": 1,
    "data": {
        "ID": "3118",
        "NAME": "Luyện Khí Cao Thủ Ở Đô Thị",
        "CHAPTER": [
            {
                "id": "1061872",
                "name": "Chương 1: Ngô Phong"
            }
        ],
        "TOTALCHAPTER": "459",
        "IMG": "https://static.cdnno.com/poster//150.jpg",
        "CAT": "Tiên Hiệp, Đô Thị",
        "AUTHOR": "Mục Dã Hương Thôn",
        "TRANS": "Suntran",
        "DESC": "Phi di&ecirc;m tẩu b&iacute;ch, một tay đ&aacute; vụn, cũng kh&ocirc;ng phải truyền thuyết. M&agrave; c&oacute; thể l&agrave;m được những n&agrave;y ở thế giới n&agrave;y bị gọi chung là luyện kh&iacute; giả.<br /><br />Luyện kh&iacute; giả, hiếm như l&aacute; m&ugrave;a thu, vạn người chưa chắc c&oacute; được một. Tr&ecirc;n thế giới cũng chỉ c&oacute; số &iacute;t người biết luyện kh&iacute; giả tồn tại.<br /><br />Ng&ocirc; Phong, văn nhược nh&aacute;t gan, kết h&ocirc;n sinh con, v&ocirc; &yacute; nhưng tiến v&agrave;o luyện kh&iacute; giả h&agrave;ng ngũ, trở th&agrave;nh luyện kh&iacute; cao thủ, từ đ&acirc;y, b&igrave;nh thản nh&acirc;n sinh thay đổi.",
        "THUMB": "https://static.cdnno.com/poster//150.jpg"
    },
    "errorCode": 0,
    "errorMessage": ""
}