{
    "success": 1,
    "data": {
        "ID": "9603",
        "NAME": "Trọng Sinh Chi Thần Đế Quy Lai",
        "CHAPTER": [
            {
                "id": "3245613",
                "name": "Chương 1: Trọng sinh thiếu niên"
            }
        ],
        "TOTALCHAPTER": "1845",
        "IMG": "https://static.cdnno.com/poster//150.jpg",
        "CAT": "Đô Thị",
        "AUTHOR": "Mã Giáp Thiên Vạn",
        "TRANS": "Nhiều Converter",
        "DESC": "Một năm kia, Trần Tiêu thi đại học thất bại, bạn gái chia tay, phụ mẫu càng là gặp tai nạn xe cộ, song song bỏ mình.<br />\r\n<br />\r\n\tTrong tuyệt vọng hắn nhảy xuống Sơn Nhai, ý đồ kết thúc cuộc đời, không nghĩ tới lại xuyên việt đến một cái thần kỳ Hoành Đại Võ Đạo Thế Giới!<br />\r\n<br />\r\n\tBa ngàn năm về sau, Trần Tiêu đã là trấn áp đương thời, quét ngang vô địch tuyệt thế đại đế, nhưng hắn lại bỏ dứt khoát bỏ qua Vạn Kiếp Bất Diệt Nguyên Thủy Chi Khu, mang theo ba ngàn năm trí nhớ trở lại thời đại thiếu niên!<br />\r\n<br />\r\n\tMột thế này, hắn không cầu quan sát vũ trụ, chỉ cầu oanh oanh liệt liệt, không phụ trước kia giai nhân!<br />\r\n<br />\r\n+ Ae Đọc Tích Cực Vote (9~10) ở cuối mỗi chương nếu có nhé..cảm ơn!!!!!!!<br />\r\n<br />\r\n+ Tình trạng: Đang ra....",
        "THUMB": "https://static.cdnno.com/poster//150.jpg"
    },
    "errorCode": 0,
    "errorMessage": ""
}