{
    "success": 1,
    "data": {
        "ID": "9763",
        "NAME": "Hành Khúc Chi Vương",
        "CHAPTER": [
            {
                "id": "3292655",
                "name": "Chương 1 : Kẻ đáng thương 0"
            }
        ],
        "TOTALCHAPTER": "27",
        "IMG": "https://static.cdnno.com/poster//150.jpg",
        "CAT": "Tiên Hiệp, Kiếm Hiệp, Huyền Ảo, Xuyên Không",
        "AUTHOR": "Thâm lam gia tử trấp",
        "TRANS": "Theanhdz",
        "DESC": "vốn cho là xuyên qua đến hoang thú hoành hành, võ giả làm đầu dị thế giới sẽ chết rất thê thảm, ai biết thế giới này lại tồn tại hành khúc loại này kỳ quái giả thiết.<br />\r\n<br />\r\n\tLàm dị thế giới các võ giả còn ở dùng thô lậu nhất nguyên thủy hành khúc tăng lên sức chiến đấu thời điểm, tự mang Địa Cầu khúc khố Hàn nhạc khinh bỉ nở nụ cười.<br />\r\n<br />\r\n\tTinh gia ngự dụng đao nhỏ sẽ nhạc dạo vang lên thì, mãn huyết phục sinh thêm sức chiến đấu tăng vọt!<br />\r\n<br />\r\n\tTên trinh thám Conan giọng chính mở ra, năng lực trinh thám trực tiếp tăng cao!<br />\r\n<br />\r\n\t97 bản Thiên Long Bát Bộ nhạc dạo —— ồ? Ta làm sao tự động học được Hàng Long Thập Bát Chưởng?<br />\r\n<br />\r\n\tMà khi [ nam nhi làm tự cường ] tấu hưởng thời gian, Hàn nhạc cảm giác mình vô địch rồi<br />\r\n<br />\r\n\t—— ai! Nói! Quốc! Nhạc! Không! Nhiên! Khúc?<br />\r\n✯✯✯✯✯✯✯✯✯✯✯✯✯✯✯✯✯✯✯✯✯✯✯✯✯✯✯✯✯✯✯✯✯✯✯✯✯✯✯✯✯✯✯✯<br />\r\nMỌI NGƯỜI ĐÁNH GIÁ 10 ĐIỂM CUỐI MỖI CHƯƠNG CHO MÌNH NHÉ, XIN CẢM ƠN<br />\r\n✯✯✯✯✯✯✯✯✯✯✯✯✯✯✯✯✯✯✯✯✯✯✯✯✯✯✯✯✯✯✯✯✯✯✯✯✯✯✯✯✯✯✯✯<br />\r\n<br />\r\n✯✯✯✯✯✯✯✯✯✯✯✯✯✯✯✯✯✯✯✯✯✯✯✯✯✯✯✯✯✯✯✯✯✯✯✯✯✯✯✯✯✯✯✯<br />\r\nMỌI NGƯỜI XEM THẤY HAY NHỚ VOTE SAO NHÉ, XIN CẢM ƠN<br />\r\n Trích Đoạn<br />\r\n<br />\r\ntop qidian",
        "THUMB": "https://static.cdnno.com/poster//150.jpg"
    },
    "errorCode": 0,
    "errorMessage": ""
}