{
    "success": 1,
    "data": {
        "ID": "7975",
        "NAME": "Chiến Phá Thương Khung",
        "CHAPTER": [
            {
                "id": "2780617",
                "name": "Tự Chương: Kíp nổ đọ sức"
            }
        ],
        "TOTALCHAPTER": "190",
        "IMG": "https://static.cdnno.com/poster//150.jpg",
        "CAT": "Võng Du",
        "AUTHOR": "Long Đại Nhân",
        "TRANS": "๖ۣۜReon",
        "DESC": "Tại không có ra trận kia tai nạn xe cộ trước đó, hắn có rất nhiều danh hiệu, khoái thủ Tước Nhân Vương, sát thần đạo tặc, vũ trụ thứ nhất mạnh, hack tuyển thủ, quán quân kẻ huỷ diệt, Tiêu thần, thần bên trong chi thần. . .<br />\r\n<br />\r\nBởi vì tai nạn xe cộ đã mất đi nghịch thiên tốc độ tay, sau đó thảm tao câu lạc bộ giải ước, phong quang vô hạn hắn, từ trên trời rơi trên mặt đất.<br />\r\n<br />\r\nBị ép cùng bát mỹ ở chung, từ bỏ đạo tặc, đổi chơi chiến sĩ, một đời đại thần còn có thể mạnh mẽ lên sao?<br />\r\n<br />\r\nKhông có người xem trọng hắn, chỉ có chính hắn.<br />\r\n<br />\r\nMặt đối với người khác chất vấn, Tiêu Viễn rất tự tin: Cái này không có gì a? Ta cảm thấy ta còn có thể a.",
        "THUMB": "https://static.cdnno.com/poster//150.jpg"
    },
    "errorCode": 0,
    "errorMessage": ""
}