{
    "success": 1,
    "data": {
        "ID": "9770",
        "NAME": "Nhất Giới Chi Chủ Phấn Đấu",
        "CHAPTER": [
            {
                "id": "3296905",
                "name": "Chương 1: Có Vô Địch Phòng Ngự Hài Nhi"
            }
        ],
        "TOTALCHAPTER": "36",
        "IMG": "https://static.cdnno.com/poster//150.jpg",
        "CAT": "Huyền Ảo, Xuyên Không",
        "AUTHOR": "Lợn Rừng Thánh Kỵ Sĩ",
        "TRANS": "yykhongloithoat",
        "DESC": "Giới thiệu vắn tắt :  tu luyện 、 chuyển kiếp 、 mua bán 、 chiến tranh …… <br />\r\n<br />\r\n　　 Từ kinh doanh một cái thế giới, đến khai thác một cái thế giới, Vương Triết tại Hư Không Vạn Giới bên trong viết lên truyền kỳ bất hủ. <br />\r\n<br />\r\n★☆★☆★☆★☆★☆★☆<br />\r\nCầu like ! <br />\r\nCầu vote 10* ! <br />\r\nCầu vote cuối chương ! <br />\r\n★☆ Xin chân thành cảm tạ ★☆★☆★☆",
        "THUMB": "https://static.cdnno.com/poster//150.jpg"
    },
    "errorCode": 0,
    "errorMessage": ""
}