{
    "success": 1,
    "data": {
        "ID": "10715",
        "NAME": "[ Tống Mạn ] Công Lược Hệ Thống.",
        "CHAPTER": [],
        "TOTALCHAPTER": "0",
        "IMG": "https://static.cdnno.com/poster//150.jpg",
        "CAT": "Võng Du, Xuyên Không, Đồng Nhân",
        "AUTHOR": "Lười Biếng Nữ.",
        "TRANS": "Nhiều Converter",
        "DESC": "Tiêu Kỳ được hệ thống lựa chọn để đi vào các nhị thứ nguyên, tiểu thuyết, phim ảnh các loại thế giới, công lược các loại nam nhân chỉ định. Sau khi hoàn thành nhiệm vụ, quay đầu lại nhìn, hóa ra ta lại hoa tâm nhiều người như vậy. Nếu vậy thì cùng nhau đi, mãi mãi nhé. . .      Chú Ý : Bài này là BL văn, YY, bàn tay vàng cùng phúc lợi cực lớn, Tom Sue. Ai dị ứng một trong mấy điều trên thỉnh Click Black. Vô cùng cảm ơn, Chu~<br />\r\nP/s: Đây là thể loại namxnam, nếu ai không đọc được xin đừng vào và đăng comments lung tung.",
        "THUMB": "https://static.cdnno.com/poster//150.jpg"
    },
    "errorCode": 0,
    "errorMessage": ""
}