{
    "success": 1,
    "data": {
        "ID": "3831",
        "NAME": "Thiên Địa Bá Khí Quyết",
        "CHAPTER": [
            {
                "id": "1331430",
                "name": "Chương 1:  Trảm thảo trừ căn!"
            }
        ],
        "TOTALCHAPTER": "802",
        "IMG": "https://static.cdnno.com/poster//150.jpg",
        "CAT": "Khoa Huyễn",
        "AUTHOR": "Ngã sửu đáo linh hồn thâm xử",
        "TRANS": "trang4mat",
        "DESC": "Th&acirc;n thể đan điền cất giữ Huyền Kh&iacute;, kh&ocirc;ng bằng d&ugrave;ng Thi&ecirc;n Địa vi đan điền, hải nạp Huyền Kh&iacute;<br /><br />Từng bước một, đi đến con đường cường giả!",
        "THUMB": "https://static.cdnno.com/poster//150.jpg"
    },
    "errorCode": 0,
    "errorMessage": ""
}