{
    "success": 1,
    "data": {
        "ID": "4479",
        "NAME": "Dị Võ Tà Thần",
        "CHAPTER": [
            {
                "id": "1598233",
                "name": "Chương 01: Ha hả xuyên qua ?"
            }
        ],
        "TOTALCHAPTER": "925",
        "IMG": "https://static.cdnno.com/poster/di-vo-ta-than/150.jpg",
        "CAT": "Huyền Ảo, Trùng Sinh",
        "AUTHOR": "Nguyệt Hoa Lệ",
        "TRANS": "๖ۣۜKing๖ۣۜKiller",
        "DESC": "Vì hồng nhan chiến đấu , vì muôn dân, trăm họ tay cầm đao Trảm Thiên địa!<br />\r\n<br />\r\n\tHoa Hạ bộ đội đặc thù xuyên qua Dị Giới biến thành hoàn khố đệ tử .<br />\r\n<br />\r\n\t Phác thảo Bá Thế kế hoạch, dùng kiếp trước dị năng khinh thường tất cả !<br />\r\n<br />\r\n\tMang theo thần bí công pháp cùng quần hùng tranh phong, diệt hết cái gọi là thiên tài, khinh thường thiên hạ người thường, chú tạo huyền thoại bất hủ .<br />\r\n<br />\r\n            Ai có thể làm khó dễ được ta ?",
        "THUMB": "https://static.cdnno.com/poster/di-vo-ta-than/150.jpg"
    },
    "errorCode": 0,
    "errorMessage": ""
}