{
    "success": 1,
    "data": {
        "ID": "11000",
        "NAME": "Nghịch Thiên Lược Đoạt Hệ Thống",
        "CHAPTER": [
            {
                "id": "3637916",
                "name": "Chương 1: Lược Đoạt Hệ Thống"
            }
        ],
        "TOTALCHAPTER": "464",
        "IMG": "https://static.cdnno.com/poster//150.jpg",
        "CAT": "Huyền Ảo, Xuyên Không, Trùng Sinh",
        "AUTHOR": "Đế Hồng",
        "TRANS": "๖ۣۜThanh ๖ۣۜPhong",
        "DESC": "Trạch nam Lý Kỳ xuyên việt đến Thần Châu Đại Lục một cái phế sài công tử trên người, dựa vào Nghịch Thiên Lược Đoạt Hệ Thống, quyền đả các lộ thiên tài, chân đá bát phương yêu nghiệt, quật khởi mạnh mẽ, cử thế vô địch .<br />\r\n<br />\r\n\tLinh đan diệu dược, thần binh lợi khí, cường lực võ kỹ, tuyệt thế công pháp, không có ý tứ ta đều muốn hết .<br />\r\n<br />\r\n\tNgươi có ta đều có thể cướp tới, ta có ngươi lại vĩnh viễn cũng có không được .<br />\r\n<br />\r\n\tTruy mỹ nữ đều có một hảo cảm thanh tiến độ, ngươi cầm cái gì cùng ta so?<br />\r\n<br />\r\n\tSao thế không phục? Không phục liền đánh ngươi, hết thảy quỳ xuống cho ta hát chinh phục!<br />\r\n<br />\r\n๖ۣۜThanh ๖ۣۜPhong đã trở lại và lại vẫn làm yy như xưa.... <br />\r\n<br />\r\nP/s: Truyện thể loại yy, main lên cấp nhanh như ngồi hỏa tiễn, mới cv 5c mà nó lên làm Nhị Giai Võ Sĩ rồi =))....<br />\r\n<br />\r\nP/s2: Các bạn qua ủng hộ mình bộ http://truyencv.com/do-thi-chi-ton-ba-chu/ nhé... /cuoi<br />\r\n<br />\r\nP/s3: Ai có nguyệt phiếu có kim đậu cứ quăng vào mình... Càng nhiều càng tốt /cuoi... Nếu có HỎA TINH CHÂU, THẤT TINH CHÂU, BỐ CÁO LỆNH, KIM SA CHÂU thì xin ủng hộ mình nhé... /cuoi... Mình sẽ bạo... ^^",
        "THUMB": "https://static.cdnno.com/poster//150.jpg"
    },
    "errorCode": 0,
    "errorMessage": ""
}