{
    "success": 1,
    "data": {
        "ID": "9641",
        "NAME": "Boss Vợ Ngài Có Thai Rùi",
        "CHAPTER": [
            {
                "id": "3255547",
                "name": "Chương 1 : Mở Đầu"
            }
        ],
        "TOTALCHAPTER": "30",
        "IMG": "https://static.cdnno.com/poster//150.jpg",
        "CAT": "Ngôn Tình, Xuyên Không",
        "AUTHOR": "Nhiều Converter",
        "TRANS": "Nhiều Converter",
        "DESC": "Văn án: Sinh ra vào hai mươi năm sau ngày tận thế, năm bốn mươi lăm tuổi từ dân chạy nạn đường phố trở thành cao thủ bậc nhất Hoa Họa.<br />\r\nTrong trận chiến cuối cùng giữa nhân loại cùng tang thi, cùng tang thi vương đồng quy vu tận, bóng tối bao trùm nhân loại gần bảy mươi năm chấm dứt, nghênh đón một tương lai mới.<br />\r\nLúc một lần nữa mở to mắt, thời gian đã qua ba ngàn năm.<br />\r\nLúc còn chưa rõ tình cảnh của chính mình thì bi kịch bị đóng gói mang tặng cho người ta.<br />\r\nCảnh một: Trên chiến trường. Một bóng đen chợt lóe, đi kèm là hàn quang sắc bén, một thể biến dị cao ba mét nháy mắt bị chẻ đôi.<br />\r\n“Em tới làm gì?” Boss xụ mặt.<br />\r\nBạn Quang nào đó bình tĩnh thu đao vào vỏ.<br />\r\n“Trong nhà không có gì chơi, ra ngoài dạo, đi ngang qua a.”<br />\r\nCảnh hai: Nhìn mặt Boss, bạn Quang nào đó trầm mặc hồi lâu rồi vươn tay chọt chọt cái mặt than của mình, nghiêm túc nói: “Tôi xấu hổ a.”<br />\r\nBoss: “… …”<br />\r\nCảnh ba: “Làm thiếu tướng phu nhân, hẳn có chút tinh thông nhạc khí đi?” Bạch Liên Hoa. (trong sáng ngây thơ như thánh nữ)<br />\r\n“Không biết.” Bạn Quang nào đó.<br />\r\n“Kia trà đạo?” Bạch Liên Hoa cười.<br />\r\n“Không biết.” Bạn Quang nào đó.<br />\r\n“Vậy cậu biết cái gì hả?” Bạch Liên Hoa đắc ý.<br />\r\nBạn Quang nào đó cúi đầu suy tư.<br />\r\nMột lát sau, hàn quang chợt lóe, một thanh trường đao dừng trước mũi Bạch Liên Hoa hai cm.<br />\r\n“Chém người có tính không?”<br />\r\nTiếng nói vừa dứt, ‘lạch cạch!’ một tiếng, cái bàn bị chẻ làm đôi.",
        "THUMB": "https://static.cdnno.com/poster//150.jpg"
    },
    "errorCode": 0,
    "errorMessage": ""
}