{
    "success": 1,
    "data": {
        "ID": "3939",
        "NAME": "Siêu Thần Hệ Thống",
        "CHAPTER": [
            {
                "id": "1418864",
                "name": "Chương 01: Siêu Thần Hệ Thống"
            }
        ],
        "TOTALCHAPTER": "540",
        "IMG": "https://static.cdnno.com/poster//150.jpg",
        "CAT": "Đô Thị",
        "AUTHOR": "Trùng 2",
        "TRANS": "Masaki1991",
        "DESC": "Nh&igrave;n thấu tho&aacute;ng một ph&aacute;t n&oacute;ng bỏng muội tử, tu luyện một điểm thần b&iacute; v&otilde; học, lắp đặt một th&acirc;n si&ecirc;u cường vũ kh&iacute;, nghi&ecirc;n cứu một &iacute;t tương lai khoa học.<br /> Lợi nhuận lợi nhuận m&oacute;n tiền nhỏ, đủ loại ti&ecirc;n thảo, luyện luyện ti&ecirc;n đan, dưỡng dưỡng thần th&uacute;.\r\n<br /> T&igrave;m xem đảo quốc (Jap) xui, hạ thấp United States America uy phong, đuổi con mắt sinh trưởng ở hốc mắt b&ecirc;n ngo&agrave;i người ngo&agrave;i h&agrave;nh tinh......\r\n<br /> Từ khi đ&atilde; nhận được Si&ecirc;u Thần Hệ Thống về sau, Mộc Du cuộc sống gia đ&igrave;nh tạm ổn tr&ocirc;i qua rất thoải m&aacute;i.\r\n<br /> Tựu l&agrave; hệ thống ở b&ecirc;n trong ngẫu nhi&ecirc;n xuất hiện một &iacute;t nhiệm vụ, lại để cho Mộc Du c&oacute; ch&uacute;t &iacute;t xấu hổ.\r\n<br /> V&iacute; dụ như, đ&ecirc;m ngự thập nữ......",
        "THUMB": "https://static.cdnno.com/poster//150.jpg"
    },
    "errorCode": 0,
    "errorMessage": ""
}