{
    "success": 1,
    "data": {
        "ID": "10761",
        "NAME": "Chung Cực Võ Hồn Tiến Hóa Hệ Thống",
        "CHAPTER": [
            {
                "id": "3572712",
                "name": "Chương 1: Chung cực Võ Hồn tiến hóa hệ thống"
            }
        ],
        "TOTALCHAPTER": "8",
        "IMG": "https://static.cdnno.com/poster//150.jpg",
        "CAT": "Huyền Ảo",
        "AUTHOR": "Thành chủ khuynh thành",
        "TRANS": "Nghĩa Phạm",
        "DESC": "Cảm xúc dâng trào, vô hạn ảo tưởng, đón gió huy kích ngàn cơn sóng, thiếu niên bất bại nhiệt huyết!<br />\r\n<br />\r\nP/S: Hố hơi sâu, truyện mới ra 43 chương",
        "THUMB": "https://static.cdnno.com/poster//150.jpg"
    },
    "errorCode": 0,
    "errorMessage": ""
}