{
    "success": 1,
    "data": {
        "ID": "6936",
        "NAME": "Vô Hạn Triệu Hoán Anime Giới",
        "CHAPTER": [
            {
                "id": "2460935",
                "name": "Chương 1: Xuyên qua ư?"
            }
        ],
        "TOTALCHAPTER": "4",
        "IMG": "https://static.cdnno.com/poster//150.jpg",
        "CAT": "Xuyên Không, Đồng Nhân",
        "AUTHOR": "trantuvan1999vn",
        "TRANS": "Nhiều Converter",
        "DESC": "À không có gì ngoài một lũ Otaku may mắn bỗng dưng xuyên không theo ý chí của đấng toàn năng triệu hồi ra toàn skill khủng để cứu lấy thế giới<br />\r\n Giới thiệu sơ lượt qua 1 chút Anh linh ư? Không cần chém thánh cũng  triệu hồi được<br />\r\nSát long thuật cần rồng dạy mới học đc không cần có tý điểm là học được ngay<br />\r\nCác vị tướng huyền thoại của liên minh giờ làm tướng của bọn ta <br />\r\nThành lập quốc gia cần quân đội ư quân đội heroes 5 không đủ ư thêm Warcraft III là đủ<br />\r\n1 thằng xuyên qua ư ? Giờ thì 2 thằng <br />\r\nKhông phải chứ sao thằng bạn thân cũng theo đít mình thế này<br />\r\nTruyện sẽ ra rất chậm tầm 3 ngày 1 chương vì mình lười đánh chữ và bận ôn thi mong các bạn thông cảm",
        "THUMB": "https://static.cdnno.com/poster//150.jpg"
    },
    "errorCode": 0,
    "errorMessage": ""
}