{
    "success": 1,
    "data": {
        "ID": "4587",
        "NAME": "Tam Quốc Chi Thiên Kiều Bách Mị",
        "CHAPTER": [
            {
                "id": "1628988",
                "name": "Chương 1: Phần đệm"
            }
        ],
        "TOTALCHAPTER": "400",
        "IMG": "https://static.cdnno.com/poster//150.jpg",
        "CAT": "Quân Sự, Lịch Sử",
        "AUTHOR": "Chung Nam Tả Liễu",
        "TRANS": "landland",
        "DESC": "Giang Sơn bao nhi&ecirc;u kiều,<br /> <br /> Dẫn v&ocirc; số Anh H&ugrave;ng cạnh khom lưng,<br /> <br /> Sinh gặp H&aacute;n Mạt loạn thế,<br /> <br /> Nam Nhi khi chấp Thanh Phong Kiếm,<br /> <br /> B&igrave;nh thi&ecirc;n hạ, an l&ecirc; d&acirc;n, định X&atilde; Tắc, Tỉnh Chưởng Thi&ecirc;n Hạ Quyền, T&uacute;y Ngọa Mỹ Nh&acirc;n Đ&ugrave;i.<br /> <br /> ~~~~~~~~~",
        "THUMB": "https://static.cdnno.com/poster//150.jpg"
    },
    "errorCode": 0,
    "errorMessage": ""
}